{"DocumentId":"NYT19980928.0173","TopicId":"NYT","Relevance":"0","Body":" BC-SPOT-BJT29-COX \n    \n\n      The Cox News Service spot news budget for Tuesday, September 29,\n1998.\n      c.1998 Cox News Service\n\n   This is the Cox News Service spot news budget for Tuesday,\nSeptember 29, 1998. We will update this budget at 6 p.m. EDT.\n\n   Separate feature and commentary budgets move at 10 a.m. EDT\nMonday-Friday. Separate sports and business budgets move at 5 p.m.\nEDT Monday-Friday.\n\n   If you have questions or need a resend, please call CoxNet, the\nCox News Service, at 404-526-5456. The night news editor, until 10\np.m. EDT, is Todd C. Duncan at 404-582-7282.\n\n   With questions about Washington-originated material, please call\nour Washington Bureau:\n\n   News editor Art Dalglish, 202-887-8338.\n\n   Foreign editor Rick Christie, 202-887-8316.\n\n   Bureau chief Andy Alexander, 202-887-8334.\n\n   Photo and graphics information and editors' names can be found\nat the end of this budget.\n\n   HURRICANE GEORGES\n\n   GEORGES _ OCEAN SPRINGS, Miss. _ The Gulf Coast groaned under\nthe fury of Hurricane Georges, which moved ashore with gusts as\nhigh as 172 mph early today as it spewed wind and rain from the\nFlorida Panhandle to Louisiana. New Orleans hoped it had avoided\nthe worst the storm could offer. No deaths or injuries had been\nreported, but National Guard troops using trucks and boats had to\nrescue about 200 people from flooded homes in the Florida\nPanhandle, where most roads were reported flooded and Interstate 10\nwas washed out near the Alabama line. The hurricane's eye,\nsurrounded by wind blowing at a sustained 105 mph, moved ashore\nthis morning at Ocean Springs, between Biloxi and Pascagoula, and\nthe National Hurricane Service in Biloxi reported a gust to 172\nmph. Within two hours, the wind started rising again at Pascagoula.\n(Marlon Manuel in Mobile/Chris Burritt in Ocean Springs, Atlanta\nJournal-Constitution). WITH MAP\n\n   w/photos. REFER TO MORE INSIDE.\n\n   WITH\n\n   BIGEASY _ NEW ORLEANS _ The Crescent City escaped the eye of\nHurricane Georges. Scene from the city. (Rochell, Atlanta\nJournal-Constitution).\n\n   FLORIDA _ PENSACOLA _ Checking out the beach erosion and scene\nalong the Florida Panhandle. (Williams., Atlanta\nJournal-Constitution). WITH MAP\n\n   CANE _ PENSACOLA _ Report on damage from Georges in the\nPanhandle. (Elmore, Palm Beach Post). 25.\n\n   INTERNATIONAL\n\n   CLINTON-MIDEAST _ WASHINGTON _ President Clinton will meet with\nIsraeli Prime Minister Bejamin Netanyahu and Palestinian Authority\nPresident Yasser Arafat at the White House Monday, expected to\npress for some small movement in the stalled Israeli-Paestinian\npeace negotiations. Developing. (Deans, Cox News Service).\n\n   EDs: To move by 6 p.m. EDT.\n\n   NATIONAL\n\n   TX-SUPREME-COURT _ WACO _ The Texas Supreme Court heard about\nsex and corruption as it held the first session outside Austin in\nmore than 100 years, in a session at Baylor in Waco. (McCarthy,\nAustin American-Statesman).\n\n   LA-NINA _ Suddenly, more drought is in doubt. Officially, the\nNational Weather Service still is calling for a La Nina winter and\nspring, which usually means drought for us. But UT aerospace\nengineers monitoring satellite data from the eastern Pacific say\nthe signs there that, in June and July, forecast a developing La\nNina are flipflopping unpredicatbly. So it might be a normal winter\nand spring for us, afterall. (Stanley, Austin American-Statesman).\n\n   DEADBEATS _ Dayton was one of seven cities chosen for a national\nstudy about unemployed fathers whose children are on welfare. The\nstudy was only marginally successful, underscroing the difficulty\nof reaching this hard-core group. (Hundley, Dayton Daily News). 12.\n\n   RUDOLPH _ ANDREWS, N.C. _ FBI agents meet with bear hunters 7\np.m. Monday to discuss ways the hunters can help in the search for\nbomb suspect Eric Robert Rudolph. (Chamberlain, AJC stringer; not\nfor use by NYT clients).\n\n   TENGRAND _ At the urging of a suburban Atlanta police chief, and\nwith the intent to take a bite out of drug dealers' proceeds, U.S.\nSen. Max Cleland has introduced a bill that would make it possible\nfor police to seize the cash of anyone carrying more than $10,000.\nThe cash is deemed seizable if, among other things, whoever has it\n``provided false information to any law enforcement officer,'' if\nit is found ``in close proximity to a measurable quantity'' of any\nillicit drug or if a drug dog ``alerts'' when sniffing it. Some\npolice organizations have praised the bill. But some police\nofficers have quietly raised objections to it, asserting that the\nbill legislates an assumption of guilt about anyone carrying large\nsums of cash and that innocent people whose cash is seized would\nhave to go to court and prove their innocence to get the money\nback. We're looking for a worthy spokesperson to take the ``con''\nside of the issue. (Payne, Atlanta Journal-Constitution).\n\n   WASHINGTON\n\n   SENIORS-SEX _ WASHINGTON _ The good news for middle-aged Baby\nBoomers is that nearly three out of four sexually active older\nAmericans say sex is as good or better after 60 as it was in their\n40s. The bad news is that fewer than half of all seniors are\nsexually active. Those are some of the results of a national survey\non senior sex released Monday by the National Council on the Aging.\n(Dart, Cox News Service).\n\n   SCHOLARSHIPS _ WASHINGTON _ The Children's Scholarship Fund,\nwhich underwrites private school scholarships for children in\nkindergarten through eighth grade, announces Monday that Atlanta\nand Dayton will be partner cities for the 1999 academic year.\n(Monroe, Cox News Service 250).\n\n   Eds: Separate stories will move to these two sites only.\n\n   Story Filed By Cox Newspapers\n\n   For Use By Clients of the New York Times News Service\n","Headline":"\n    \n","Text":["\n   This is the Cox News Service spot news budget for Tuesday,\nSeptember 29, 1998. We will update this budget at 6 p.m. EDT.\n","\n   Separate feature and commentary budgets move at 10 a.m. EDT\nMonday-Friday. Separate sports and business budgets move at 5 p.m.\nEDT Monday-Friday.\n","\n   If you have questions or need a resend, please call CoxNet, the\nCox News Service, at 404-526-5456. The night news editor, until 10\np.m. EDT, is Todd C. Duncan at 404-582-7282.\n","\n   With questions about Washington-originated material, please call\nour Washington Bureau:\n","\n   News editor Art Dalglish, 202-887-8338.\n","\n   Foreign editor Rick Christie, 202-887-8316.\n","\n   Bureau chief Andy Alexander, 202-887-8334.\n","\n   Photo and graphics information and editors' names can be found\nat the end of this budget.\n","\n   HURRICANE GEORGES\n","\n   GEORGES _ OCEAN SPRINGS, Miss. _ The Gulf Coast groaned under\nthe fury of Hurricane Georges, which moved ashore with gusts as\nhigh as 172 mph early today as it spewed wind and rain from the\nFlorida Panhandle to Louisiana. New Orleans hoped it had avoided\nthe worst the storm could offer. No deaths or injuries had been\nreported, but National Guard troops using trucks and boats had to\nrescue about 200 people from flooded homes in the Florida\nPanhandle, where most roads were reported flooded and Interstate 10\nwas washed out near the Alabama line. The hurricane's eye,\nsurrounded by wind blowing at a sustained 105 mph, moved ashore\nthis morning at Ocean Springs, between Biloxi and Pascagoula, and\nthe National Hurricane Service in Biloxi reported a gust to 172\nmph. Within two hours, the wind started rising again at Pascagoula.\n(Marlon Manuel in Mobile/Chris Burritt in Ocean Springs, Atlanta\nJournal-Constitution). WITH MAP\n","\n   w/photos. REFER TO MORE INSIDE.\n","\n   WITH\n","\n   BIGEASY _ NEW ORLEANS _ The Crescent City escaped the eye of\nHurricane Georges. Scene from the city. (Rochell, Atlanta\nJournal-Constitution).\n","\n   FLORIDA _ PENSACOLA _ Checking out the beach erosion and scene\nalong the Florida Panhandle. (Williams., Atlanta\nJournal-Constitution). WITH MAP\n","\n   CANE _ PENSACOLA _ Report on damage from Georges in the\nPanhandle. (Elmore, Palm Beach Post). 25.\n","\n   INTERNATIONAL\n","\n   CLINTON-MIDEAST _ WASHINGTON _ President Clinton will meet with\nIsraeli Prime Minister Bejamin Netanyahu and Palestinian Authority\nPresident Yasser Arafat at the White House Monday, expected to\npress for some small movement in the stalled Israeli-Paestinian\npeace negotiations. Developing. (Deans, Cox News Service).\n","\n   EDs: To move by 6 p.m. EDT.\n","\n   NATIONAL\n","\n   TX-SUPREME-COURT _ WACO _ The Texas Supreme Court heard about\nsex and corruption as it held the first session outside Austin in\nmore than 100 years, in a session at Baylor in Waco. (McCarthy,\nAustin American-Statesman).\n","\n   LA-NINA _ Suddenly, more drought is in doubt. Officially, the\nNational Weather Service still is calling for a La Nina winter and\nspring, which usually means drought for us. But UT aerospace\nengineers monitoring satellite data from the eastern Pacific say\nthe signs there that, in June and July, forecast a developing La\nNina are flipflopping unpredicatbly. So it might be a normal winter\nand spring for us, afterall. (Stanley, Austin American-Statesman).\n","\n   DEADBEATS _ Dayton was one of seven cities chosen for a national\nstudy about unemployed fathers whose children are on welfare. The\nstudy was only marginally successful, underscroing the difficulty\nof reaching this hard-core group. (Hundley, Dayton Daily News). 12.\n","\n   RUDOLPH _ ANDREWS, N.C. _ FBI agents meet with bear hunters 7\np.m. Monday to discuss ways the hunters can help in the search for\nbomb suspect Eric Robert Rudolph. (Chamberlain, AJC stringer; not\nfor use by NYT clients).\n","\n   TENGRAND _ At the urging of a suburban Atlanta police chief, and\nwith the intent to take a bite out of drug dealers' proceeds, U.S.\nSen. Max Cleland has introduced a bill that would make it possible\nfor police to seize the cash of anyone carrying more than $10,000.\nThe cash is deemed seizable if, among other things, whoever has it\n``provided false information to any law enforcement officer,'' if\nit is found ``in close proximity to a measurable quantity'' of any\nillicit drug or if a drug dog ``alerts'' when sniffing it. Some\npolice organizations have praised the bill. But some police\nofficers have quietly raised objections to it, asserting that the\nbill legislates an assumption of guilt about anyone carrying large\nsums of cash and that innocent people whose cash is seized would\nhave to go to court and prove their innocence to get the money\nback. We're looking for a worthy spokesperson to take the ``con''\nside of the issue. (Payne, Atlanta Journal-Constitution).\n","\n   WASHINGTON\n","\n   SENIORS-SEX _ WASHINGTON _ The good news for middle-aged Baby\nBoomers is that nearly three out of four sexually active older\nAmericans say sex is as good or better after 60 as it was in their\n40s. The bad news is that fewer than half of all seniors are\nsexually active. Those are some of the results of a national survey\non senior sex released Monday by the National Council on the Aging.\n(Dart, Cox News Service).\n","\n   SCHOLARSHIPS _ WASHINGTON _ The Children's Scholarship Fund,\nwhich underwrites private school scholarships for children in\nkindergarten through eighth grade, announces Monday that Atlanta\nand Dayton will be partner cities for the 1999 academic year.\n(Monroe, Cox News Service 250).\n","\n   Eds: Separate stories will move to these two sites only.\n","\n   Story Filed By Cox Newspapers\n","\n   For Use By Clients of the New York Times News Service\n"]}