{"DocumentId":"NYT19990411.0003","TopicId":"NYT","Relevance":"0","Body":" BC-COMMENTARY-SLUGLIST-CLOSER \n   Here is a list of commentary items stories that moved on\nSaturday, April 10, on The N.Y. Times News Service.\n\n   Included is story number, keyword, wordage, time sent (Eastern),\npriority code and category code.\n\n   COMMENTARY\n\n   A3379 BC-EDIT-KOSOVO-WAR-NYT 802 19:08 U K\n\n   EDITORIAL: WAR IN AN ERA OF ETHNIC CONFLICT\n\n   A3367 BC-EDIT-MENTALLY-ILL-NYT 434 18:37 U K\n\n   EDITORIAL: MEDICATING THE MENTALLY ILL\n\n   A3311 BC-EDIT-OBSERVER-NYT 667 16:31 U K\n\n   EDITORIAL OBSERVER: PAYING MORE TAXES WITHOUT COMPLAINTS\n","Headline":null,"Text":["\n   Here is a list of commentary items stories that moved on\nSaturday, April 10, on The N.Y. Times News Service.\n","\n   Included is story number, keyword, wordage, time sent (Eastern),\npriority code and category code.\n","\n   COMMENTARY\n","\n   A3379 BC-EDIT-KOSOVO-WAR-NYT 802 19:08 U K\n","\n   EDITORIAL: WAR IN AN ERA OF ETHNIC CONFLICT\n","\n   A3367 BC-EDIT-MENTALLY-ILL-NYT 434 18:37 U K\n","\n   EDITORIAL: MEDICATING THE MENTALLY ILL\n","\n   A3311 BC-EDIT-OBSERVER-NYT 667 16:31 U K\n","\n   EDITORIAL OBSERVER: PAYING MORE TAXES WITHOUT COMPLAINTS\n",""]}